Pokelib/__init__.py
Pokelib/pokemon.csv
Pokelib/random_pokemon.py
Pokelib-1.0.1.dist-info/METADATA
Pokelib-1.0.1.dist-info/WHEEL
Pokelib-1.0.1.dist-info/top_level.txt
Pokelib-1.0.1.dist-info/RECORD
